Metadata-Version: 2.1
Name: tap-surveymonkey
Version: 2.1.0
Summary: Singer.io tap for extracting data
Home-page: http://singer.io
Author: Stitch
Classifier: Programming Language :: Python :: 3 :: Only
Provides-Extra: dev
License-File: LICENSE
